fuclib/__init__.py
fuclib/ezfuc.py
fuclib/ezmongo.py
fuclib/ezmssql.py
fuclib/ezmssqlodb.py
fuclib/ezmysql.py
fuclib-0.1.2.dist-info/METADATA
fuclib-0.1.2.dist-info/WHEEL
fuclib-0.1.2.dist-info/top_level.txt
fuclib-0.1.2.dist-info/RECORD
