Metadata-Version: 2.1
Name: fuclib
Version: 0.1.2
Summary: A simple, for its own method library.
Home-page: https://elanpy.com
Author: eamonn
Author-email: china.eamonn@gmail.com
License: MIT
Platform: UNKNOWN
Classifier: License :: OSI Approved :: MIT License
Classifier: Programming Language :: Python
Classifier: Programming Language :: Python :: 3
Classifier: Programming Language :: Python :: 3.6
Classifier: Programming Language :: Python :: Implementation :: CPython
Classifier: Programming Language :: Python :: Implementation :: PyPy
Requires-Python: >=3.4.0
Requires-Dist: pymysql
Requires-Dist: pymssql
Requires-Dist: pymongo
Requires-Dist: munch
Requires-Dist: pyodbc
Requires-Dist: requests
